<annotation>
	<folder>doc_images_hassan</folder>
	<filename>fulltext (1)_17.jpg</filename>
	<path>C:\Users\100119\Desktop\DATA_EXTRACTION_DOCUMENT\data\doc_images_hassan\fulltext (1)_17.jpg</path>
	<source>
		<database>Unknown</database>
	</source>
	<size>
		<width>300</width>
		<height>300</height>
		<depth>1</depth>
	</size>
	<segmented>0</segmented>
	<object>
		<name>text</name>
		<pose>Unspecified</pose>
		<truncated>0</truncated>
		<difficult>0</difficult>
		<bndbox>
			<xmin>57</xmin>
			<ymin>7</ymin>
			<xmax>248</xmax>
			<ymax>29</ymax>
		</bndbox>
	</object>
	<object>
		<name>table</name>
		<pose>Unspecified</pose>
		<truncated>0</truncated>
		<difficult>0</difficult>
		<bndbox>
			<xmin>57</xmin>
			<ymin>32</ymin>
			<xmax>240</xmax>
			<ymax>84</ymax>
		</bndbox>
	</object>
	<object>
		<name>text</name>
		<pose>Unspecified</pose>
		<truncated>0</truncated>
		<difficult>0</difficult>
		<bndbox>
			<xmin>49</xmin>
			<ymin>93</ymin>
			<xmax>247</xmax>
			<ymax>102</ymax>
		</bndbox>
	</object>
	<object>
		<name>table</name>
		<pose>Unspecified</pose>
		<truncated>0</truncated>
		<difficult>0</difficult>
		<bndbox>
			<xmin>51</xmin>
			<ymin>103</ymin>
			<xmax>247</xmax>
			<ymax>256</ymax>
		</bndbox>
	</object>
</annotation>
