<annotation>
	<folder>train</folder>
	<filename>IMG_1674_1.jpg</filename>
	<path>C:\Users\100119\Desktop\DATA_EXTRACTION_DOCUMENT\data\22-11-2019\train\IMG_1674_1.jpg</path>
	<source>
		<database>Unknown</database>
	</source>
	<size>
		<width>300</width>
		<height>300</height>
		<depth>1</depth>
	</size>
	<segmented>0</segmented>
	<object>
		<name>text</name>
		<pose>Unspecified</pose>
		<truncated>0</truncated>
		<difficult>0</difficult>
		<bndbox>
			<xmin>13</xmin>
			<ymin>40</ymin>
			<xmax>267</xmax>
			<ymax>108</ymax>
		</bndbox>
	</object>
	<object>
		<name>text</name>
		<pose>Unspecified</pose>
		<truncated>0</truncated>
		<difficult>0</difficult>
		<bndbox>
			<xmin>18</xmin>
			<ymin>109</ymin>
			<xmax>186</xmax>
			<ymax>146</ymax>
		</bndbox>
	</object>
	<object>
		<name>text</name>
		<pose>Unspecified</pose>
		<truncated>0</truncated>
		<difficult>0</difficult>
		<bndbox>
			<xmin>17</xmin>
			<ymin>147</ymin>
			<xmax>279</xmax>
			<ymax>205</ymax>
		</bndbox>
	</object>
	<object>
		<name>image</name>
		<pose>Unspecified</pose>
		<truncated>0</truncated>
		<difficult>0</difficult>
		<bndbox>
			<xmin>171</xmin>
			<ymin>29</ymin>
			<xmax>279</xmax>
			<ymax>46</ymax>
		</bndbox>
	</object>
</annotation>
