<annotation>
	<folder>pdf_image_22-11-2019</folder>
	<filename>new_doc_res_251.jpg</filename>
	<path>C:\Users\100119\Desktop\DATA_EXTRACTION_DOCUMENT\data\22-11-2019\pdf_image_22-11-2019\new_doc_res_251.jpg</path>
	<source>
		<database>Unknown</database>
	</source>
	<size>
		<width>300</width>
		<height>300</height>
		<depth>3</depth>
	</size>
	<segmented>0</segmented>
	<object>
		<name>text</name>
		<pose>Unspecified</pose>
		<truncated>0</truncated>
		<difficult>0</difficult>
		<bndbox>
			<xmin>121</xmin>
			<ymin>7</ymin>
			<xmax>186</xmax>
			<ymax>27</ymax>
		</bndbox>
	</object>
	<object>
		<name>table</name>
		<pose>Unspecified</pose>
		<truncated>0</truncated>
		<difficult>0</difficult>
		<bndbox>
			<xmin>22</xmin>
			<ymin>34</ymin>
			<xmax>289</xmax>
			<ymax>90</ymax>
		</bndbox>
	</object>
	<object>
		<name>table</name>
		<pose>Unspecified</pose>
		<truncated>0</truncated>
		<difficult>0</difficult>
		<bndbox>
			<xmin>16</xmin>
			<ymin>87</ymin>
			<xmax>295</xmax>
			<ymax>148</ymax>
		</bndbox>
	</object>
	<object>
		<name>table</name>
		<pose>Unspecified</pose>
		<truncated>0</truncated>
		<difficult>0</difficult>
		<bndbox>
			<xmin>17</xmin>
			<ymin>147</ymin>
			<xmax>296</xmax>
			<ymax>183</ymax>
		</bndbox>
	</object>
	<object>
		<name>table</name>
		<pose>Unspecified</pose>
		<truncated>0</truncated>
		<difficult>0</difficult>
		<bndbox>
			<xmin>18</xmin>
			<ymin>183</ymin>
			<xmax>299</xmax>
			<ymax>235</ymax>
		</bndbox>
	</object>
	<object>
		<name>table</name>
		<pose>Unspecified</pose>
		<truncated>1</truncated>
		<difficult>0</difficult>
		<bndbox>
			<xmin>17</xmin>
			<ymin>236</ymin>
			<xmax>300</xmax>
			<ymax>288</ymax>
		</bndbox>
	</object>
	<object>
		<name>image</name>
		<pose>Unspecified</pose>
		<truncated>0</truncated>
		<difficult>0</difficult>
		<bndbox>
			<xmin>14</xmin>
			<ymin>5</ymin>
			<xmax>56</xmax>
			<ymax>19</ymax>
		</bndbox>
	</object>
</annotation>
